httpgo/__init__.py
httpgo/auth.py
httpgo/cli.py
httpgo/client.py
httpgo/config.py
httpgo/formatter.py
httpgo/models.py
httpgo/parser.py
httpgo/variables.py
httpgo_cli-0.1.2.dist-info/METADATA
httpgo_cli-0.1.2.dist-info/WHEEL
httpgo_cli-0.1.2.dist-info/entry_points.txt
httpgo_cli-0.1.2.dist-info/licenses/LICENSE
httpgo_cli-0.1.2.dist-info/RECORD
