Metadata-Version: 2.4
Name: httpgo-cli
Version: 0.1.2
Summary: A powerful HTTP CLI that supports .http files, variables, and multiple authentication methods
Project-URL: Homepage, https://github.com/feesec/httpgo
Project-URL: Repository, https://github.com/feesec/httpgo
Project-URL: Issues, https://github.com/feesec/httpgo/issues
Author-email: Felix <feexsec@gmail.com>
License: MIT
License-File: LICENSE
Keywords: api,cli,client,http,rest
Classifier: Development Status :: 4 - Beta
Classifier: Environment :: Console
Classifier: Intended Audience :: Developers
Classifier: License :: OSI Approved :: MIT License
Classifier: Programming Language :: Python :: 3.11
Classifier: Programming Language :: Python :: 3.12
Classifier: Topic :: Internet :: WWW/HTTP
Classifier: Topic :: Software Development :: Testing
Requires-Python: >=3.11
Requires-Dist: httpx>=0.27.0
Requires-Dist: pynacl>=1.5.0
Requires-Dist: python-dotenv>=1.0.0
Requires-Dist: pyyaml>=6.0.0
Requires-Dist: rich>=13.7.0
Requires-Dist: tomli-w>=1.0.0
Requires-Dist: typer>=0.12.0
